__init__.py
acc_levy.py
behavioural.py
benefit_rules.py
benefits.py
data_export.py
demographic_modelling.py
dynamic_simulation.py
historic_tax_search.py
historical_data.py
inflation.py
investment_tax.py
microsim.py
optimisation.py
parameter_validation.py
parameters.py
payroll_deductions.py
performance_optimizations.py
pipeline.py
policy_reports.py
reporting.py
reporting_framework.py
rule_registry.py
rules_engine.py
sensitivity_analysis.py
simulation.py
tax_calculator.py
tax_credits.py
tax_rules.py
validation.py
value_of_information.py
wff_logic.py
wff_microsim.py
wff_microsim_main.py
wff_rules.py
api/__init__.py
api/celery_app.py
api/dashboard_endpoints.py
api/main.py
api/tasks.py
nztaxmicrosim-0.3.1.dist-info/METADATA
nztaxmicrosim-0.3.1.dist-info/WHEEL
nztaxmicrosim-0.3.1.dist-info/top_level.txt
nztaxmicrosim-0.3.1.dist-info/RECORD
