Metadata-Version: 2.4
Name: nztaxmicrosim
Version: 0.3.1
Summary: A Python-based microsimulation model for the New Zealand tax and transfer system.
Author-email: NZ Tax Microsimulation Team <contact@nztaxmicrosim.org>
Maintainer-email: NZ Tax Microsimulation Team <contact@nztaxmicrosim.org>
License: MIT
Project-URL: Homepage, https://github.com/Treasury-AnZ/nztaxmicrosim
Project-URL: Repository, https://github.com/Treasury-AnZ/nztaxmicrosim
Project-URL: Documentation, https://github.com/Treasury-AnZ/nztaxmicrosim/blob/main/README.md
Project-URL: Bug Tracker, https://github.com/Treasury-AnZ/nztaxmicrosim/issues
Project-URL: Changelog, https://github.com/Treasury-AnZ/nztaxmicrosim/blob/main/CHANGELOG.md
Keywords: taxation,microsimulation,new-zealand,policy-analysis,economics
Classifier: Development Status :: 4 - Beta
Classifier: Intended Audience :: Science/Research
Classifier: Intended Audience :: Developers
Classifier: Topic :: Scientific/Engineering :: Information Analysis
Classifier: Topic :: Office/Business :: Financial
Classifier: License :: OSI Approved :: MIT License
Classifier: Programming Language :: Python :: 3
Classifier: Programming Language :: Python :: 3.9
Classifier: Programming Language :: Python :: 3.10
Classifier: Programming Language :: Python :: 3.11
Classifier: Programming Language :: Python :: 3.12
Classifier: Operating System :: OS Independent
Requires-Python: >=3.9
Requires-Dist: pandas
Requires-Dist: numpy
Requires-Dist: optuna
Requires-Dist: pydantic
Requires-Dist: matplotlib
Requires-Dist: seaborn
Requires-Dist: joblib
Requires-Dist: kedro
Requires-Dist: scipy
Requires-Dist: tabulate>=0.9.0
Requires-Dist: requests
Requires-Dist: pyyaml
Requires-Dist: wbdata
Requires-Dist: fastapi
Requires-Dist: uvicorn
Requires-Dist: celery
Requires-Dist: redis
Requires-Dist: faker
Requires-Dist: httpx
Requires-Dist: python-multipart
Requires-Dist: jinja2>=3.0.0
Requires-Dist: openpyxl>=3.0.0
Requires-Dist: psutil>=5.8.0
Requires-Dist: memory-profiler>=0.60.0
Provides-Extra: research
Requires-Dist: pyreadstat>=1.2.0; extra == "research"
Requires-Dist: pyreadr>=0.4.0; extra == "research"
Provides-Extra: dev
Requires-Dist: pytest>=7.0.0; extra == "dev"
Requires-Dist: pytest-cov>=4.0.0; extra == "dev"
Requires-Dist: pytest-benchmark>=4.0.0; extra == "dev"
Requires-Dist: pytest-mock>=3.10.0; extra == "dev"
Requires-Dist: pytest-html>=4.0.0; extra == "dev"
Requires-Dist: syrupy>=4.0.0; extra == "dev"
Requires-Dist: pre-commit>=3.0.0; extra == "dev"
Requires-Dist: ruff>=0.1.0; extra == "dev"
Requires-Dist: mypy>=1.0.0; extra == "dev"
Requires-Dist: pyright>=1.1.0; extra == "dev"
Requires-Dist: tox>=4.0.0; extra == "dev"
Requires-Dist: tox-gh-actions>=2.0.0; extra == "dev"
Requires-Dist: pandera>=0.18.0; extra == "dev"
Requires-Dist: hypothesis>=6.0.0; extra == "dev"
Requires-Dist: mutmut>=2.0.0; extra == "dev"
Requires-Dist: lizard>=1.0.0; extra == "dev"
Requires-Dist: nbqa>=1.7.0; extra == "dev"
Requires-Dist: nbstripout>=0.6.0; extra == "dev"
Requires-Dist: safety>=2.0.0; extra == "dev"
Requires-Dist: semgrep>=1.0.0; extra == "dev"
Requires-Dist: darglint>=1.8.0; extra == "dev"
Requires-Dist: pytest-order>=1.0.0; extra == "dev"
Requires-Dist: black>=23.0.0; extra == "dev"
Requires-Dist: isort>=5.0.0; extra == "dev"
Requires-Dist: editorconfig-checker>=2.0.0; extra == "dev"
Provides-Extra: all
Requires-Dist: nztaxmicrosim[dev,research]; extra == "all"
